{
  "generated_at": "2019-04-04T04:51:06+00:00",
  "schema": "http:\/\/schemas.sportradar.com\/bsa\/soccer\/v1\/json\/endpoints\/soccer\/match_summary.json",
  "sport_event": {
    "id": "sr:match:16514885",
    "scheduled": "2019-03-06T20:00:00+00:00",
    "start_time_tbd": false,
    "tournament_round": {
      "type": "cup",
      "name": "round_of_16",
      "cup_round_match_number": 2,
      "cup_round_matches": 2,
      "other_match_id": "sr:match:16514883",
      "phase": "final_phase"
    },
    "season": {
      "id": "sr:season:54533",
      "name": "UEFA Champions League 18\/19",
      "start_date": "2018-06-26",
      "end_date": "2019-06-02",
      "year": "18\/19",
      "tournament_id": "sr:tournament:7"
    },
    "tournament": {
      "id": "sr:tournament:7",
      "name": "UEFA Champions League",
      "sport": {
        "id": "sr:sport:1",
        "name": "Soccer"
      },
      "category": {
        "id": "sr:category:393",
        "name": "International Clubs"
      }
    },
    "competitors": [
      {
        "id": "sr:competitor:1644",
        "name": "Paris Saint-Germain",
        "country": "France",
        "country_code": "FRA",
        "abbreviation": "PSG",
        "qualifier": "home"
      },
      {
        "id": "sr:competitor:35",
        "name": "Manchester United",
        "country": "England",
        "country_code": "ENG",
        "abbreviation": "MUN",
        "qualifier": "away"
      }
    ],
    "venue": {
      "id": "sr:venue:843",
      "name": "Parc Des Princes",
      "capacity": 45000,
      "city_name": "Paris",
      "country_name": "France",
      "map_coordinates": "48.841389,2.253056",
      "country_code": "FRA"
    }
  },
  "sport_event_conditions": {
    "referee": {
      "id": "sr:referee:52368",
      "name": "Skomina, Damir",
      "nationality": "Slovenia",
      "country_code": "SVN"
    },
    "referee_assistants": [
      {
        "type": "first_assistant_referee",
        "id": "sr:referee:130339",
        "name": "Praprotnik, Jure",
        "nationality": "Slovenia",
        "country_code": "SVN"
      },
      {
        "type": "second_assistant_referee",
        "id": "sr:referee:88901",
        "name": "Vukan, Robert",
        "nationality": "Slovenia",
        "country_code": "SVN"
      },
      {
        "type": "fourth_official",
        "id": "sr:referee:67047",
        "name": "Jug, Matej",
        "nationality": "Slovenia",
        "country_code": "SVN"
      },
      {
        "type": "video_assistant_referee",
        "id": "sr:referee:130998",
        "name": "Irrati, Massimiliano",
        "nationality": "Italy",
        "country_code": "ITA"
      }
    ],
    "venue": {
      "id": "sr:venue:843",
      "name": "Parc Des Princes",
      "capacity": 45000,
      "city_name": "Paris",
      "country_name": "France",
      "map_coordinates": "48.841389,2.253056",
      "country_code": "FRA"
    },
    "attendance": 47441,
    "weather_info": {
      "pitch": "good",
      "weather_conditions": "medium"
    }
  },
  "sport_event_status": {
    "status": "closed",
    "match_status": "ended",
    "home_score": 1,
    "away_score": 3,
    "winner_id": "sr:competitor:35",
    "aggregate_home_score": 3,
    "aggregate_away_score": 3,
    "aggregate_winner_id": "sr:competitor:35",
    "period_scores": [
      {
        "home_score": 1,
        "away_score": 2,
        "type": "regular_period",
        "number": 1
      },
      {
        "home_score": 0,
        "away_score": 1,
        "type": "regular_period",
        "number": 2
      }
    ]
  },
  "statistics": {
    "teams": [
      {
        "id": "sr:competitor:1644",
        "name": "Paris Saint-Germain",
        "abbreviation": "PSG",
        "qualifier": "home",
        "statistics": {
          "ball_possession": 68,
          "free_kicks": 17,
          "throw_ins": 16,
          "goal_kicks": 4,
          "shots_blocked": 2,
          "shots_on_target": 4,
          "shots_off_target": 5,
          "corner_kicks": 4,
          "fouls": 8,
          "shots_saved": 1,
          "offsides": 4,
          "yellow_cards": 3,
          "injuries": 1
        },
        "players": [
          {
            "id": "sr:player:2069",
            "name": "Buffon, Gianluigi",
            "substituted_in": 0,
            "substituted_out": 0,
            "goals_scored": 0,
            "assists": 0,
            "own_goals": 0,
            "yellow_cards": 0,
            "yellow_red_cards": 0,
            "red_cards": 0,
            "goal_line_clearances": 0,
            "interceptions": 0,
            "chances_created": 0,
            "crosses_successful": 0,
            "crosses_total": 0,
            "passes_short_successful": 0,
            "passes_medium_successful": 10,
            "passes_long_successful": 0,
            "passes_short_total": 0,
            "passes_medium_total": 10,
            "passes_long_total": 2,
            "duels_header_successful": 0,
            "duels_sprint_successful": 0,
            "duels_tackle_successful": 0,
            "duels_header_total": 0,
            "duels_sprint_total": 0,
            "duels_tackle_total": 0,
            "goals_conceded": 3,
            "shots_faced_saved": 1,
            "shots_faced_total": 4,
            "penalties_faced": 1,
            "penalties_saved": 0,
            "fouls_committed": 0,
            "was_fouled": 0,
            "offsides": 0,
            "shots_on_goal": 0,
            "shots_off_goal": 0,
            "shots_blocked": 0,
            "minutes_played": 90,
            "performance_score": 4.01,
            "goals_by_head": 0,
            "goals_by_penalty": 0
          },
          {
            "id": "sr:player:281277",
            "name": "Kehrer, Thilo",
            "substituted_in": 0,
            "substituted_out": 1,
            "goals_scored": 0,
            "assists": 0,
            "own_goals": 0,
            "yellow_cards": 0,
            "yellow_red_cards": 0,
            "red_cards": 0,
            "goal_line_clearances": 0,
            "interceptions": 0,
            "chances_created": 0,
            "crosses_successful": 0,
            "crosses_total": 0,
            "passes_short_successful": 7,
            "passes_medium_successful": 77,
            "passes_long_successful": 0,
            "passes_short_total": 8,
            "passes_medium_total": 80,
            "passes_long_total": 0,
            "duels_header_successful": 2,
            "duels_sprint_successful": 0,
            "duels_tackle_successful": 2,
            "duels_header_total": 2,
            "duels_sprint_total": 0,
            "duels_tackle_total": 4,
            "goals_conceded": 2,
            "fouls_committed": 1,
            "was_fouled": 0,
            "offsides": 0,
            "shots_on_goal": 0,
            "shots_off_goal": 0,
            "shots_blocked": 0,
            "minutes_played": 70,
            "performance_score": 6.04,
            "goals_by_head": 0,
            "goals_by_penalty": 0
          },
          {
            "id": "sr:player:33541",
            "name": "Silva, Thiago",
            "substituted_in": 0,
            "substituted_out": 0,
            "goals_scored": 0,
            "assists": 0,
            "own_goals": 0,
            "yellow_cards": 0,
            "yellow_red_cards": 0,
            "red_cards": 0,
            "goal_line_clearances": 0,
            "interceptions": 0,
            "chances_created": 0,
            "crosses_successful": 0,
            "crosses_total": 0,
            "passes_short_successful": 3,
            "passes_medium_successful": 96,
            "passes_long_successful": 2,
            "passes_short_total": 4,
            "passes_medium_total": 101,
            "passes_long_total": 3,
            "duels_header_successful": 2,
            "duels_sprint_successful": 0,
            "duels_tackle_successful": 3,
            "duels_header_total": 3,
            "duels_sprint_total": 1,
            "duels_tackle_total": 3,
            "goals_conceded": 3,
            "fouls_committed": 0,
            "was_fouled": 1,
            "offsides": 0,
            "shots_on_goal": 0,
            "shots_off_goal": 1,
            "shots_blocked": 0,
            "minutes_played": 90,
            "performance_score": 6.28,
            "goals_by_head": 0,
            "goals_by_penalty": 0
          },
          {
            "id": "sr:player:352916",
            "name": "Kimpembe, Presnel",
            "substituted_in": 0,
            "substituted_out": 0,
            "goals_scored": 0,
            "assists": 0,
            "own_goals": 0,
            "yellow_cards": 0,
            "yellow_red_cards": 0,
            "red_cards": 0,
            "goal_line_clearances": 0,
            "interceptions": 0,
            "chances_created": 0,
            "crosses_successful": 0,
            "crosses_total": 0,
            "passes_short_successful": 9,
            "passes_medium_successful": 66,
            "passes_long_successful": 0,
            "passes_short_total": 9,
            "passes_medium_total": 67,
            "passes_long_total": 3,
            "duels_header_successful": 1,
            "duels_sprint_successful": 1,
            "duels_tackle_successful": 1,
            "duels_header_total": 2,
            "duels_sprint_total": 1,
            "duels_tackle_total": 6,
            "goals_conceded": 3,
            "fouls_committed": 2,
            "was_fouled": 0,
            "offsides": 0,
            "shots_on_goal": 0,
            "shots_off_goal": 0,
            "shots_blocked": 0,
            "minutes_played": 90,
            "performance_score": 3.65,
            "goals_by_head": 0,
            "goals_by_penalty": 0
          },
          {
            "id": "sr:player:96368",
            "name": "Bernat, Juan",
            "substituted_in": 0,
            "substituted_out": 0,
            "goals_scored": 1,
            "assists": 0,
            "own_goals": 0,
            "yellow_cards": 0,
            "yellow_red_cards": 0,
            "red_cards": 0,
            "goal_line_clearances": 0,
            "interceptions": 2,
            "chances_created": 0,
            "crosses_successful": 2,
            "crosses_total": 5,
            "passes_short_successful": 12,
            "passes_medium_successful": 36,
            "passes_long_successful": 1,
            "passes_short_total": 12,
            "passes_medium_total": 38,
            "passes_long_total": 2,
            "duels_header_successful": 2,
            "duels_sprint_successful": 0,
            "duels_tackle_successful": 4,
            "duels_header_total": 3,
            "duels_sprint_total": 0,
            "duels_tackle_total": 7,
            "goals_conceded": 3,
            "fouls_committed": 0,
            "was_fouled": 1,
            "offsides": 0,
            "shots_on_goal": 2,
            "shots_off_goal": 1,
            "shots_blocked": 0,
            "minutes_played": 90,
            "performance_score": 7.89,
            "goals_by_head": 0,
            "goals_by_penalty": 0
          },
          {
            "id": "sr:player:4419",
            "name": "Alves, Dani",
            "substituted_in": 0,
            "substituted_out": 1,
            "goals_scored": 0,
            "assists": 0,
            "own_goals": 0,
            "yellow_cards": 0,
            "yellow_red_cards": 0,
            "red_cards": 0,
            "goal_line_clearances": 0,
            "interceptions": 0,
            "chances_created": 1,
            "crosses_successful": 3,
            "crosses_total": 9,
            "passes_short_successful": 16,
            "passes_medium_successful": 82,
            "passes_long_successful": 1,
            "passes_short_total": 17,
            "passes_medium_total": 88,
            "passes_long_total": 1,
            "duels_header_successful": 0,
            "duels_sprint_successful": 2,
            "duels_tackle_successful": 1,
            "duels_header_total": 2,
            "duels_sprint_total": 2,
            "duels_tackle_total": 4,
            "goals_conceded": 3,
            "fouls_committed": 1,
            "was_fouled": 3,
            "offsides": 0,
            "shots_on_goal": 0,
            "shots_off_goal": 1,
            "shots_blocked": 0,
            "minutes_played": 90,
            "performance_score": 6.08,
            "goals_by_head": 0,
            "goals_by_penalty": 0
          },
          {
            "id": "sr:player:126691",
            "name": "Verratti, Marco",
            "substituted_in": 0,
            "substituted_out": 0,
            "goals_scored": 0,
            "assists": 0,
            "own_goals": 0,
            "yellow_cards": 0,
            "yellow_red_cards": 0,
            "red_cards": 0,
            "goal_line_clearances": 0,
            "interceptions": 1,
            "chances_created": 0,
            "crosses_successful": 0,
            "crosses_total": 1,
            "passes_short_successful": 12,
            "passes_medium_successful": 77,
            "passes_long_successful": 0,
            "passes_short_total": 13,
            "passes_medium_total": 84,
            "passes_long_total": 3,
            "duels_header_successful": 0,
            "duels_sprint_successful": 0,
            "duels_tackle_successful": 10,
            "duels_header_total": 0,
            "duels_sprint_total": 0,
            "duels_tackle_total": 15,
            "goals_conceded": 3,
            "fouls_committed": 1,
            "was_fouled": 6,
            "offsides": 0,
            "shots_on_goal": 0,
            "shots_off_goal": 0,
            "shots_blocked": 0,
            "minutes_played": 90,
            "performance_score": 6.36,
            "goals_by_head": 0,
            "goals_by_penalty": 0
          },
          {
            "id": "sr:player:155995",
            "name": "Marquinhos",
            "substituted_in": 0,
            "substituted_out": 0,
            "goals_scored": 0,
            "assists": 0,
            "own_goals": 0,
            "yellow_cards": 1,
            "yellow_red_cards": 0,
            "red_cards": 0,
            "goal_line_clearances": 0,
            "interceptions": 0,
            "chances_created": 0,
            "crosses_successful": 0,
            "crosses_total": 1,
            "passes_short_successful": 6,
            "passes_medium_successful": 35,
            "passes_long_successful": 2,
            "passes_short_total": 7,
            "passes_medium_total": 38,
            "passes_long_total": 2,
            "duels_header_successful": 1,
            "duels_sprint_successful": 0,
            "duels_tackle_successful": 2,
            "duels_header_total": 2,
            "duels_sprint_total": 0,
            "duels_tackle_total": 4,
            "goals_conceded": 3,
            "fouls_committed": 1,
            "was_fouled": 1,
            "offsides": 0,
            "shots_on_goal": 0,
            "shots_off_goal": 0,
            "shots_blocked": 0,
            "minutes_played": 90,
            "performance_score": 4.18,
            "goals_by_head": 0,
            "goals_by_penalty": 0
          },
          {
            "id": "sr:player:142680",
            "name": "Draxler, Julian",
            "substituted_in": 0,
            "substituted_out": 1,
            "goals_scored": 0,
            "assists": 0,
            "own_goals": 0,
            "yellow_cards": 0,
            "yellow_red_cards": 0,
            "red_cards": 0,
            "goal_line_clearances": 0,
            "interceptions": 1,
            "chances_created": 2,
            "crosses_successful": 2,
            "crosses_total": 6,
            "passes_short_successful": 8,
            "passes_medium_successful": 34,
            "passes_long_successful": 0,
            "passes_short_total": 10,
            "passes_medium_total": 35,
            "passes_long_total": 0,
            "duels_header_successful": 0,
            "duels_sprint_successful": 1,
            "duels_tackle_successful": 2,
            "duels_header_total": 0,
            "duels_sprint_total": 1,
            "duels_tackle_total": 7,
            "goals_conceded": 2,
            "fouls_committed": 0,
            "was_fouled": 0,
            "offsides": 1,
            "shots_on_goal": 0,
            "shots_off_goal": 0,
            "shots_blocked": 0,
            "minutes_played": 70,
            "performance_score": 5.81,
            "goals_by_head": 0,
            "goals_by_penalty": 0
          },
          {
            "id": "sr:player:30027",
            "name": "Di Maria, Angel",
            "substituted_in": 0,
            "substituted_out": 0,
            "goals_scored": 0,
            "assists": 0,
            "own_goals": 0,
            "yellow_cards": 1,
            "yellow_red_cards": 0,
            "red_cards": 0,
            "goal_line_clearances": 0,
            "interceptions": 0,
            "chances_created": 4,
            "crosses_successful": 3,
            "crosses_total": 10,
            "passes_short_successful": 8,
            "passes_medium_successful": 41,
            "passes_long_successful": 0,
            "passes_short_total": 12,
            "passes_medium_total": 44,
            "passes_long_total": 0,
            "duels_header_successful": 0,
            "duels_sprint_successful": 0,
            "duels_tackle_successful": 6,
            "duels_header_total": 0,
            "duels_sprint_total": 0,
            "duels_tackle_total": 12,
            "goals_conceded": 3,
            "fouls_committed": 2,
            "was_fouled": 1,
            "offsides": 1,
            "shots_on_goal": 1,
            "shots_off_goal": 1,
            "shots_blocked": 1,
            "minutes_played": 90,
            "performance_score": 5.7,
            "goals_by_head": 0,
            "goals_by_penalty": 0
          },
          {
            "id": "sr:player:796046",
            "name": "Mbappe, Kylian",
            "substituted_in": 0,
            "substituted_out": 0,
            "goals_scored": 0,
            "assists": 1,
            "own_goals": 0,
            "yellow_cards": 0,
            "yellow_red_cards": 0,
            "red_cards": 0,
            "goal_line_clearances": 0,
            "interceptions": 1,
            "chances_created": 2,
            "crosses_successful": 1,
            "crosses_total": 2,
            "passes_short_successful": 3,
            "passes_medium_successful": 24,
            "passes_long_successful": 0,
            "passes_short_total": 5,
            "passes_medium_total": 27,
            "passes_long_total": 0,
            "duels_header_successful": 0,
            "duels_sprint_successful": 0,
            "duels_tackle_successful": 2,
            "duels_header_total": 1,
            "duels_sprint_total": 0,
            "duels_tackle_total": 7,
            "goals_conceded": 3,
            "fouls_committed": 0,
            "was_fouled": 0,
            "offsides": 2,
            "shots_on_goal": 0,
            "shots_off_goal": 1,
            "shots_blocked": 1,
            "minutes_played": 90,
            "performance_score": 6.12,
            "goals_by_head": 0,
            "goals_by_penalty": 0
          },
          {
            "id": "sr:player:255389",
            "name": "Paredes, Leandro",
            "substituted_in": 1,
            "substituted_out": 0,
            "goals_scored": 0,
            "assists": 0,
            "own_goals": 0,
            "yellow_cards": 1,
            "yellow_red_cards": 0,
            "red_cards": 0,
            "goal_line_clearances": 0,
            "interceptions": 0,
            "chances_created": 0,
            "crosses_successful": 0,
            "crosses_total": 0,
            "passes_short_successful": 0,
            "passes_medium_successful": 15,
            "passes_long_successful": 1,
            "passes_short_total": 0,
            "passes_medium_total": 15,
            "passes_long_total": 2,
            "duels_header_successful": 0,
            "duels_sprint_successful": 0,
            "duels_tackle_successful": 2,
            "duels_header_total": 0,
            "duels_sprint_total": 0,
            "duels_tackle_total": 4,
            "goals_conceded": 1,
            "fouls_committed": 1,
            "was_fouled": 2,
            "offsides": 0,
            "shots_on_goal": 0,
            "shots_off_goal": 0,
            "shots_blocked": 0,
            "minutes_played": 20,
            "performance_score": 5.27,
            "goals_by_head": 0,
            "goals_by_penalty": 0
          },
          {
            "id": "sr:player:128587",
            "name": "Meunier, Thomas",
            "substituted_in": 1,
            "substituted_out": 0,
            "goals_scored": 0,
            "assists": 0,
            "own_goals": 0,
            "yellow_cards": 0,
            "yellow_red_cards": 0,
            "red_cards": 0,
            "goal_line_clearances": 0,
            "interceptions": 0,
            "chances_created": 0,
            "crosses_successful": 0,
            "crosses_total": 2,
            "passes_short_successful": 0,
            "passes_medium_successful": 15,
            "passes_long_successful": 0,
            "passes_short_total": 1,
            "passes_medium_total": 19,
            "passes_long_total": 1,
            "duels_header_successful": 1,
            "duels_sprint_successful": 1,
            "duels_tackle_successful": 0,
            "duels_header_total": 1,
            "duels_sprint_total": 1,
            "duels_tackle_total": 0,
            "goals_conceded": 1,
            "fouls_committed": 0,
            "was_fouled": 0,
            "offsides": 0,
            "shots_on_goal": 1,
            "shots_off_goal": 0,
            "shots_blocked": 0,
            "minutes_played": 20,
            "performance_score": 4.89,
            "goals_by_head": 0,
            "goals_by_penalty": 0
          },
          {
            "id": "sr:player:21521",
            "name": "Cavani, Edinson",
            "substituted_in": 1,
            "substituted_out": 0,
            "goals_scored": 0,
            "assists": 0,
            "own_goals": 0,
            "yellow_cards": 0,
            "yellow_red_cards": 0,
            "red_cards": 0,
            "goal_line_clearances": 0,
            "interceptions": 0,
            "chances_created": 0,
            "crosses_successful": 0,
            "crosses_total": 0,
            "passes_short_successful": 0,
            "passes_medium_successful": 1,
            "passes_long_successful": 0,
            "passes_short_total": 0,
            "passes_medium_total": 1,
            "passes_long_total": 0,
            "duels_header_successful": 0,
            "duels_sprint_successful": 0,
            "duels_tackle_successful": 0,
            "duels_header_total": 0,
            "duels_sprint_total": 0,
            "duels_tackle_total": 0,
            "goals_conceded": 0,
            "fouls_committed": 0,
            "was_fouled": 0,
            "offsides": 0,
            "shots_on_goal": 0,
            "shots_off_goal": 0,
            "shots_blocked": 0,
            "minutes_played": 0,
            "performance_score": 0,
            "goals_by_head": 0,
            "goals_by_penalty": 0
          }
        ]
      },
      {
        "id": "sr:competitor:35",
        "name": "Manchester United",
        "abbreviation": "MUN",
        "qualifier": "away",
        "statistics": {
          "ball_possession": 32,
          "fouls": 15,
          "shots_on_target": 4,
          "throw_ins": 23,
          "goal_kicks": 9,
          "shots_saved": 3,
          "free_kicks": 12,
          "offsides": 2,
          "shots_blocked": 1,
          "injuries": 1,
          "yellow_cards": 1
        },
        "players": [
          {
            "id": "sr:player:69378",
            "name": "De Gea, David",
            "substituted_in": 0,
            "substituted_out": 0,
            "goals_scored": 0,
            "assists": 0,
            "own_goals": 0,
            "yellow_cards": 0,
            "yellow_red_cards": 0,
            "red_cards": 0,
            "goal_line_clearances": 0,
            "interceptions": 0,
            "chances_created": 0,
            "crosses_successful": 0,
            "crosses_total": 0,
            "passes_short_successful": 0,
            "passes_medium_successful": 8,
            "passes_long_successful": 5,
            "passes_short_total": 0,
            "passes_medium_total": 8,
            "passes_long_total": 22,
            "duels_header_successful": 0,
            "duels_sprint_successful": 0,
            "duels_tackle_successful": 0,
            "duels_header_total": 0,
            "duels_sprint_total": 0,
            "duels_tackle_total": 0,
            "goals_conceded": 1,
            "shots_faced_saved": 3,
            "shots_faced_total": 4,
            "penalties_faced": 0,
            "penalties_saved": 0,
            "fouls_committed": 0,
            "was_fouled": 0,
            "offsides": 0,
            "shots_on_goal": 0,
            "shots_off_goal": 0,
            "shots_blocked": 0,
            "minutes_played": 90,
            "performance_score": 6.1,
            "goals_by_head": 0,
            "goals_by_penalty": 0
          },
          {
            "id": "sr:player:143334",
            "name": "Lindelof, Victor",
            "substituted_in": 0,
            "substituted_out": 0,
            "goals_scored": 0,
            "assists": 0,
            "own_goals": 0,
            "yellow_cards": 0,
            "yellow_red_cards": 0,
            "red_cards": 0,
            "goal_line_clearances": 1,
            "interceptions": 2,
            "chances_created": 0,
            "crosses_successful": 0,
            "crosses_total": 0,
            "passes_short_successful": 1,
            "passes_medium_successful": 20,
            "passes_long_successful": 0,
            "passes_short_total": 2,
            "passes_medium_total": 22,
            "passes_long_total": 2,
            "duels_header_successful": 0,
            "duels_sprint_successful": 0,
            "duels_tackle_successful": 1,
            "duels_header_total": 0,
            "duels_sprint_total": 0,
            "duels_tackle_total": 1,
            "goals_conceded": 1,
            "fouls_committed": 0,
            "was_fouled": 0,
            "offsides": 0,
            "shots_on_goal": 0,
            "shots_off_goal": 0,
            "shots_blocked": 0,
            "minutes_played": 90,
            "performance_score": 6.02,
            "goals_by_head": 0,
            "goals_by_penalty": 0
          },
          {
            "id": "sr:player:47741",
            "name": "Smalling, Chris",
            "substituted_in": 0,
            "substituted_out": 0,
            "goals_scored": 0,
            "assists": 0,
            "own_goals": 0,
            "yellow_cards": 0,
            "yellow_red_cards": 0,
            "red_cards": 0,
            "goal_line_clearances": 1,
            "interceptions": 0,
            "chances_created": 0,
            "crosses_successful": 0,
            "crosses_total": 0,
            "passes_short_successful": 1,
            "passes_medium_successful": 19,
            "passes_long_successful": 1,
            "passes_short_total": 2,
            "passes_medium_total": 26,
            "passes_long_total": 4,
            "duels_header_successful": 2,
            "duels_sprint_successful": 0,
            "duels_tackle_successful": 4,
            "duels_header_total": 2,
            "duels_sprint_total": 0,
            "duels_tackle_total": 5,
            "goals_conceded": 1,
            "fouls_committed": 0,
            "was_fouled": 0,
            "offsides": 0,
            "shots_on_goal": 0,
            "shots_off_goal": 0,
            "shots_blocked": 0,
            "minutes_played": 90,
            "performance_score": 5.55,
            "goals_by_head": 0,
            "goals_by_penalty": 0
          },
          {
            "id": "sr:player:606346",
            "name": "Bailly, Eric",
            "substituted_in": 0,
            "substituted_out": 1,
            "goals_scored": 0,
            "assists": 0,
            "own_goals": 0,
            "yellow_cards": 0,
            "yellow_red_cards": 0,
            "red_cards": 0,
            "goal_line_clearances": 0,
            "interceptions": 0,
            "chances_created": 0,
            "crosses_successful": 0,
            "crosses_total": 0,
            "passes_short_successful": 0,
            "passes_medium_successful": 4,
            "passes_long_successful": 1,
            "passes_short_total": 0,
            "passes_medium_total": 5,
            "passes_long_total": 2,
            "duels_header_successful": 0,
            "duels_sprint_successful": 0,
            "duels_tackle_successful": 3,
            "duels_header_total": 0,
            "duels_sprint_total": 0,
            "duels_tackle_total": 5,
            "goals_conceded": 1,
            "fouls_committed": 0,
            "was_fouled": 1,
            "offsides": 0,
            "shots_on_goal": 0,
            "shots_off_goal": 0,
            "shots_blocked": 0,
            "minutes_played": 36,
            "performance_score": 5.41,
            "goals_by_head": 0,
            "goals_by_penalty": 0
          },
          {
            "id": "sr:player:190839",
            "name": "Shaw, Luke",
            "substituted_in": 0,
            "substituted_out": 0,
            "goals_scored": 0,
            "assists": 0,
            "own_goals": 0,
            "yellow_cards": 1,
            "yellow_red_cards": 0,
            "red_cards": 0,
            "goal_line_clearances": 0,
            "interceptions": 1,
            "chances_created": 0,
            "crosses_successful": 0,
            "crosses_total": 1,
            "passes_short_successful": 5,
            "passes_medium_successful": 26,
            "passes_long_successful": 1,
            "passes_short_total": 6,
            "passes_medium_total": 37,
            "passes_long_total": 2,
            "duels_header_successful": 0,
            "duels_sprint_successful": 0,
            "duels_tackle_successful": 5,
            "duels_header_total": 0,
            "duels_sprint_total": 2,
            "duels_tackle_total": 6,
            "goals_conceded": 1,
            "fouls_committed": 2,
            "was_fouled": 0,
            "offsides": 0,
            "shots_on_goal": 0,
            "shots_off_goal": 0,
            "shots_blocked": 0,
            "minutes_played": 90,
            "performance_score": 4.07,
            "goals_by_head": 0,
            "goals_by_penalty": 0
          },
          {
            "id": "sr:player:243623",
            "name": "Fred",
            "substituted_in": 0,
            "substituted_out": 0,
            "goals_scored": 0,
            "assists": 0,
            "own_goals": 0,
            "yellow_cards": 0,
            "yellow_red_cards": 0,
            "red_cards": 0,
            "goal_line_clearances": 0,
            "interceptions": 2,
            "chances_created": 0,
            "crosses_successful": 0,
            "crosses_total": 0,
            "passes_short_successful": 1,
            "passes_medium_successful": 32,
            "passes_long_successful": 0,
            "passes_short_total": 2,
            "passes_medium_total": 35,
            "passes_long_total": 1,
            "duels_header_successful": 0,
            "duels_sprint_successful": 0,
            "duels_tackle_successful": 4,
            "duels_header_total": 0,
            "duels_sprint_total": 0,
            "duels_tackle_total": 9,
            "goals_conceded": 1,
            "fouls_committed": 2,
            "was_fouled": 2,
            "offsides": 0,
            "shots_on_goal": 0,
            "shots_off_goal": 0,
            "shots_blocked": 0,
            "minutes_played": 90,
            "performance_score": 5.54,
            "goals_by_head": 0,
            "goals_by_penalty": 0
          },
          {
            "id": "sr:player:10589",
            "name": "Young, Ashley",
            "substituted_in": 0,
            "substituted_out": 1,
            "goals_scored": 0,
            "assists": 0,
            "own_goals": 0,
            "yellow_cards": 0,
            "yellow_red_cards": 0,
            "red_cards": 0,
            "goal_line_clearances": 1,
            "interceptions": 0,
            "chances_created": 0,
            "crosses_successful": 0,
            "crosses_total": 0,
            "passes_short_successful": 2,
            "passes_medium_successful": 25,
            "passes_long_successful": 2,
            "passes_short_total": 5,
            "passes_medium_total": 30,
            "passes_long_total": 2,
            "duels_header_successful": 0,
            "duels_sprint_successful": 0,
            "duels_tackle_successful": 0,
            "duels_header_total": 0,
            "duels_sprint_total": 0,
            "duels_tackle_total": 4,
            "goals_conceded": 1,
            "fouls_committed": 0,
            "was_fouled": 0,
            "offsides": 0,
            "shots_on_goal": 0,
            "shots_off_goal": 0,
            "shots_blocked": 0,
            "minutes_played": 87,
            "performance_score": 4.24,
            "goals_by_head": 0,
            "goals_by_penalty": 0
          },
          {
            "id": "sr:player:908372",
            "name": "McTominay, Scott",
            "substituted_in": 0,
            "substituted_out": 0,
            "goals_scored": 0,
            "assists": 0,
            "own_goals": 0,
            "yellow_cards": 0,
            "yellow_red_cards": 0,
            "red_cards": 0,
            "goal_line_clearances": 0,
            "interceptions": 1,
            "chances_created": 0,
            "crosses_successful": 0,
            "crosses_total": 0,
            "passes_short_successful": 4,
            "passes_medium_successful": 22,
            "passes_long_successful": 0,
            "passes_short_total": 6,
            "passes_medium_total": 23,
            "passes_long_total": 0,
            "duels_header_successful": 0,
            "duels_sprint_successful": 0,
            "duels_tackle_successful": 6,
            "duels_header_total": 0,
            "duels_sprint_total": 2,
            "duels_tackle_total": 9,
            "goals_conceded": 1,
            "fouls_committed": 4,
            "was_fouled": 1,
            "offsides": 0,
            "shots_on_goal": 0,
            "shots_off_goal": 0,
            "shots_blocked": 0,
            "minutes_played": 90,
            "performance_score": 5.26,
            "goals_by_head": 0,
            "goals_by_penalty": 0
          },
          {
            "id": "sr:player:903830",
            "name": "Rashford, Marcus",
            "substituted_in": 0,
            "substituted_out": 0,
            "goals_scored": 1,
            "penalty_goals_scored": 1,
            "assists": 0,
            "own_goals": 0,
            "yellow_cards": 0,
            "yellow_red_cards": 0,
            "red_cards": 0,
            "goal_line_clearances": 0,
            "interceptions": 2,
            "chances_created": 1,
            "crosses_successful": 0,
            "crosses_total": 2,
            "passes_short_successful": 5,
            "passes_medium_successful": 20,
            "passes_long_successful": 0,
            "passes_short_total": 6,
            "passes_medium_total": 26,
            "passes_long_total": 1,
            "duels_header_successful": 1,
            "duels_sprint_successful": 0,
            "duels_tackle_successful": 3,
            "duels_header_total": 4,
            "duels_sprint_total": 0,
            "duels_tackle_total": 9,
            "goals_conceded": 1,
            "fouls_committed": 0,
            "was_fouled": 1,
            "offsides": 2,
            "shots_on_goal": 2,
            "shots_off_goal": 0,
            "shots_blocked": 0,
            "minutes_played": 90,
            "performance_score": 6.44,
            "goals_by_head": 0,
            "goals_by_penalty": 1
          },
          {
            "id": "sr:player:285949",
            "name": "Pereira, Andreas",
            "substituted_in": 0,
            "substituted_out": 1,
            "goals_scored": 0,
            "assists": 0,
            "own_goals": 0,
            "yellow_cards": 0,
            "yellow_red_cards": 0,
            "red_cards": 0,
            "goal_line_clearances": 0,
            "interceptions": 0,
            "chances_created": 1,
            "crosses_successful": 0,
            "crosses_total": 1,
            "passes_short_successful": 1,
            "passes_medium_successful": 13,
            "passes_long_successful": 0,
            "passes_short_total": 2,
            "passes_medium_total": 17,
            "passes_long_total": 0,
            "duels_header_successful": 2,
            "duels_sprint_successful": 0,
            "duels_tackle_successful": 6,
            "duels_header_total": 2,
            "duels_sprint_total": 0,
            "duels_tackle_total": 8,
            "goals_conceded": 1,
            "fouls_committed": 3,
            "was_fouled": 3,
            "offsides": 0,
            "shots_on_goal": 0,
            "shots_off_goal": 0,
            "shots_blocked": 0,
            "minutes_played": 80,
            "performance_score": 5.99,
            "goals_by_head": 0,
            "goals_by_penalty": 0
          },
          {
            "id": "sr:player:78893",
            "name": "Lukaku, Romelu",
            "substituted_in": 0,
            "substituted_out": 0,
            "goals_scored": 2,
            "assists": 0,
            "own_goals": 0,
            "yellow_cards": 0,
            "yellow_red_cards": 0,
            "red_cards": 0,
            "goal_line_clearances": 0,
            "interceptions": 1,
            "chances_created": 0,
            "crosses_successful": 0,
            "crosses_total": 0,
            "passes_short_successful": 4,
            "passes_medium_successful": 10,
            "passes_long_successful": 0,
            "passes_short_total": 5,
            "passes_medium_total": 14,
            "passes_long_total": 0,
            "duels_header_successful": 2,
            "duels_sprint_successful": 1,
            "duels_tackle_successful": 2,
            "duels_header_total": 6,
            "duels_sprint_total": 2,
            "duels_tackle_total": 6,
            "goals_conceded": 1,
            "fouls_committed": 1,
            "was_fouled": 0,
            "offsides": 0,
            "shots_on_goal": 2,
            "shots_off_goal": 0,
            "shots_blocked": 0,
            "minutes_played": 90,
            "performance_score": 7.87,
            "goals_by_head": 0,
            "goals_by_penalty": 0
          },
          {
            "id": "sr:player:817522",
            "name": "Dalot, Diogo",
            "substituted_in": 1,
            "substituted_out": 0,
            "goals_scored": 0,
            "assists": 0,
            "own_goals": 0,
            "yellow_cards": 0,
            "yellow_red_cards": 0,
            "red_cards": 0,
            "goal_line_clearances": 0,
            "interceptions": 0,
            "chances_created": 0,
            "crosses_successful": 1,
            "crosses_total": 4,
            "passes_short_successful": 3,
            "passes_medium_successful": 15,
            "passes_long_successful": 0,
            "passes_short_total": 3,
            "passes_medium_total": 16,
            "passes_long_total": 2,
            "duels_header_successful": 0,
            "duels_sprint_successful": 0,
            "duels_tackle_successful": 3,
            "duels_header_total": 1,
            "duels_sprint_total": 0,
            "duels_tackle_total": 6,
            "goals_conceded": 0,
            "fouls_committed": 1,
            "was_fouled": 0,
            "offsides": 0,
            "shots_on_goal": 0,
            "shots_off_goal": 0,
            "shots_blocked": 1,
            "minutes_played": 54,
            "performance_score": 5.37,
            "goals_by_head": 0,
            "goals_by_penalty": 0
          },
          {
            "id": "sr:player:934232",
            "name": "Chong, Tahith",
            "substituted_in": 1,
            "substituted_out": 0,
            "goals_scored": 0,
            "assists": 0,
            "own_goals": 0,
            "yellow_cards": 0,
            "yellow_red_cards": 0,
            "red_cards": 0,
            "goal_line_clearances": 0,
            "interceptions": 0,
            "chances_created": 0,
            "crosses_successful": 0,
            "crosses_total": 0,
            "passes_short_successful": 0,
            "passes_medium_successful": 3,
            "passes_long_successful": 0,
            "passes_short_total": 0,
            "passes_medium_total": 4,
            "passes_long_total": 0,
            "duels_header_successful": 0,
            "duels_sprint_successful": 0,
            "duels_tackle_successful": 1,
            "duels_header_total": 0,
            "duels_sprint_total": 0,
            "duels_tackle_total": 5,
            "goals_conceded": 0,
            "fouls_committed": 1,
            "was_fouled": 0,
            "offsides": 0,
            "shots_on_goal": 0,
            "shots_off_goal": 0,
            "shots_blocked": 0,
            "minutes_played": 10,
            "performance_score": 5.35,
            "goals_by_head": 0,
            "goals_by_penalty": 0
          },
          {
            "id": "sr:player:1546543",
            "name": "Greenwood, Mason",
            "substituted_in": 1,
            "substituted_out": 0,
            "goals_scored": 0,
            "assists": 0,
            "own_goals": 0,
            "yellow_cards": 0,
            "yellow_red_cards": 0,
            "red_cards": 0,
            "goal_line_clearances": 0,
            "interceptions": 0,
            "chances_created": 0,
            "crosses_successful": 0,
            "crosses_total": 0,
            "passes_short_successful": 0,
            "passes_medium_successful": 0,
            "passes_long_successful": 0,
            "passes_short_total": 0,
            "passes_medium_total": 0,
            "passes_long_total": 0,
            "duels_header_successful": 0,
            "duels_sprint_successful": 0,
            "duels_tackle_successful": 0,
            "duels_header_total": 1,
            "duels_sprint_total": 0,
            "duels_tackle_total": 0,
            "goals_conceded": 0,
            "fouls_committed": 1,
            "was_fouled": 0,
            "offsides": 0,
            "shots_on_goal": 0,
            "shots_off_goal": 0,
            "shots_blocked": 0,
            "minutes_played": 3,
            "performance_score": 0,
            "goals_by_head": 0,
            "goals_by_penalty": 0
          }
        ]
      }
    ]
  }
}